alembic_utils/__init__.py
alembic_utils/depends.py
alembic_utils/exceptions.py
alembic_utils/experimental/__init__.py
alembic_utils/experimental/_collect_instances.py
alembic_utils/on_entity_mixin.py
alembic_utils/pg_extension.py
alembic_utils/pg_function.py
alembic_utils/pg_grant_table.py
alembic_utils/pg_materialized_view.py
alembic_utils/pg_policy.py
alembic_utils/pg_trigger.py
alembic_utils/pg_view.py
alembic_utils/py.typed
alembic_utils/replaceable_entity.py
alembic_utils/reversible_op.py
alembic_utils/simulate.py
alembic_utils/statement.py
alembic_utils/testbase.py
alembic_utils-0.8.7.dist-info/LICENSE
alembic_utils-0.8.7.dist-info/METADATA
alembic_utils-0.8.7.dist-info/WHEEL
alembic_utils-0.8.7.dist-info/RECORD
