Metadata-Version: 2.3
Name: alembic_utils
Version: 0.8.7
Summary: A sqlalchemy/alembic extension for migrating procedures and views
License: MIT
Author: Oliver Rice
Author-email: oliver@oliverrice.com
Requires-Python: >=3.9
Classifier: Development Status :: 4 - Beta
Classifier: Intended Audience :: Developers
Classifier: License :: OSI Approved :: MIT License
Classifier: Programming Language :: Python :: 3
Classifier: Programming Language :: Python :: 3.9
Classifier: Programming Language :: Python :: 3.10
Classifier: Programming Language :: Python :: 3.11
Classifier: Programming Language :: Python :: 3.12
Classifier: Programming Language :: Python :: 3.13
Classifier: Programming Language :: SQL
Requires-Dist: alembic (>=1.9)
Requires-Dist: flupy
Requires-Dist: parse (>=1.8.4)
Requires-Dist: sqlalchemy (>=1.4)
Requires-Dist: typing_extensions
Project-URL: PyPI, https://pypi.org/project/alembic-utils/
